LICENSE
MANIFEST.in
README.md
requirements.txt
setup.cfg
setup.py
ezdashboard/__init__.py
ezdashboard/__meta__.py
ezdashboard/build.py
ezdashboard/dashboard.py
ezdashboard/div.py
ezdashboard/elements.py
ezdashboard/header.py
ezdashboard/list_div.py
ezdashboard/list_js.py
ezdashboard/misc.py
ezdashboard/row.py
ezdashboard/tab.py
ezdashboard/title.py
ezdashboard.egg-info/PKG-INFO
ezdashboard.egg-info/SOURCES.txt
ezdashboard.egg-info/dependency_links.txt
ezdashboard.egg-info/not-zip-safe
ezdashboard.egg-info/requires.txt
ezdashboard.egg-info/top_level.txt
ezdashboard/templates/custom.css
ezdashboard/templates/dashboard.template.html
ezdashboard/templates/main.css