Metadata-Version: 1.1
Name: ezdashboard
Version: 0.2.9
Summary: Easy dashboard creaation from raw HTML components
Home-page: https://gitlab.com/oscar6echo/ezdashboard
Author: oscar6echo
Author-email: olivier.borderies@sgcib.com
License: MIT
Download-URL: https://gitlab.com/oscar6echo/ezdashboard/repository/archive.tar.gz?ref=0.2.9
Keywords: python,dashboard,jinja,html,js,css
Platform: UNKNOWN
Classifier: Development Status :: 4 - Beta
Classifier: License :: OSI Approved :: MIT License
Classifier: Programming Language :: Python :: 2.7
Classifier: Programming Language :: Python :: 3.5
Classifier: Programming Language :: Python :: 3.6
